up_fast_downward-0.5.2.dist-info/RECORD
up_fast_downward-0.5.2.dist-info/WHEEL
up_fast_downward-0.5.2.dist-info/top_level.txt
up_fast_downward-0.5.2.dist-info/METADATA
up_fast_downward-0.5.2.dist-info/licenses/LICENSE.txt
up_fast_downward/fast_downward.py
up_fast_downward/__init__.py
up_fast_downward/_custom_build.py
up_fast_downward/utils.py
up_fast_downward/fast_downward_grounder.py
up_fast_downward/downward/LICENSE.md
up_fast_downward/downward/README.md
up_fast_downward/downward/fast-downward.py
up_fast_downward/downward/driver/conftest.py
up_fast_downward/downward/driver/portfolio_runner.py
up_fast_downward/downward/driver/version.py
up_fast_downward/downward/driver/limits.py
up_fast_downward/downward/driver/util.py
up_fast_downward/downward/driver/arguments.py
up_fast_downward/downward/driver/__init__.py
up_fast_downward/downward/driver/cleanup.py
up_fast_downward/downward/driver/plan_manager.py
up_fast_downward/downward/driver/aliases.py
up_fast_downward/downward/driver/run_components.py
up_fast_downward/downward/driver/returncodes.py
up_fast_downward/downward/driver/tests.py
up_fast_downward/downward/driver/main.py
up_fast_downward/downward/driver/call.py
up_fast_downward/downward/driver/portfolios/seq_sat_fdss_1.py
up_fast_downward/downward/driver/portfolios/seq_sat_fdss_2014.py
up_fast_downward/downward/driver/portfolios/seq_opt_fdss_1.py
up_fast_downward/downward/driver/portfolios/seq_sat_fdss_2018.py
up_fast_downward/downward/driver/portfolios/seq_sat_fdss_2023.py
up_fast_downward/downward/driver/portfolios/seq_opt_fdss_2.py
up_fast_downward/downward/driver/portfolios/seq_sat_fdss_2.py
up_fast_downward/downward/driver/portfolios/seq_opt_merge_and_shrink.py
up_fast_downward/downward/builds/release/bin/downward
up_fast_downward/downward/builds/release/bin/translate/options.py
up_fast_downward/downward/builds/release/bin/translate/simplify.py
up_fast_downward/downward/builds/release/bin/translate/variable_order.py
up_fast_downward/downward/builds/release/bin/translate/normalize.py
up_fast_downward/downward/builds/release/bin/translate/tools.py
up_fast_downward/downward/builds/release/bin/translate/graph.py
