Metadata-Version: 2.4
Name: up_fast_downward
Version: 0.5.2
Summary: Unified Planning Integration of the Fast Downward planning system
Author: UNIBAS Team
Maintainer-email: Gabriele Röger <gabriele.roeger@unibas.ch>
License: GPL-3.0-only
Project-URL: Homepage, https://github.com/aiplan4eu/up-fast-downward/
Classifier: Development Status :: 5 - Production/Stable
Classifier: License :: OSI Approved :: GNU General Public License v3 (GPLv3)
Classifier: Programming Language :: Python :: 3
Classifier: Topic :: Scientific/Engineering :: Artificial Intelligence
Requires-Python: >=3.9
License-File: LICENSE.txt
Requires-Dist: setuptools>=59.6.0
Dynamic: license-file
